pantsbuild.pants.contrib.node-1.30.4-py3.6-nspkg.pth
pants/contrib/node/__init__.py
pants/contrib/node/register.py
pants/contrib/node/target_types.py
pants/contrib/node/subsystems/__init__.py
pants/contrib/node/subsystems/command.py
pants/contrib/node/subsystems/eslint.py
pants/contrib/node/subsystems/node_distribution.py
pants/contrib/node/subsystems/package_managers.py
pants/contrib/node/subsystems/yarnpkg_distribution.py
pants/contrib/node/subsystems/resolvers/__init__.py
pants/contrib/node/subsystems/resolvers/node_preinstalled_module_resolver.py
pants/contrib/node/subsystems/resolvers/node_resolver_base.py
pants/contrib/node/subsystems/resolvers/npm_resolver.py
pants/contrib/node/targets/__init__.py
pants/contrib/node/targets/node_bundle.py
pants/contrib/node/targets/node_module.py
pants/contrib/node/targets/node_package.py
pants/contrib/node/targets/node_preinstalled_module.py
pants/contrib/node/targets/node_remote_module.py
pants/contrib/node/targets/node_test.py
pants/contrib/node/tasks/__init__.py
pants/contrib/node/tasks/javascript_style.py
pants/contrib/node/tasks/node_build.py
pants/contrib/node/tasks/node_bundle.py
pants/contrib/node/tasks/node_install.py
pants/contrib/node/tasks/node_paths.py
pants/contrib/node/tasks/node_repl.py
pants/contrib/node/tasks/node_resolve.py
pants/contrib/node/tasks/node_run.py
pants/contrib/node/tasks/node_task.py
pants/contrib/node/tasks/node_test.py
pantsbuild.pants.contrib.node-1.30.4.dist-info/METADATA
pantsbuild.pants.contrib.node-1.30.4.dist-info/RECORD
pantsbuild.pants.contrib.node-1.30.4.dist-info/WHEEL
pantsbuild.pants.contrib.node-1.30.4.dist-info/entry_points.txt
pantsbuild.pants.contrib.node-1.30.4.dist-info/namespace_packages.txt
pantsbuild.pants.contrib.node-1.30.4.dist-info/top_level.txt
pantsbuild.pants.contrib.node-1.30.4.dist-info/zip-safe
